[
  {
    "id": "1",
    "node": "消灭方形30个",
    "taskicon": "icon_task_1",
    "textID": "56",
    "taskinfo": "Hit a square of 50",
    "tasktype": "1",
    "target": "1",
    "count": "50",
    "limit": "0",
    "reward": "2"
  },
  {
    "id": "2",
    "node": "消灭三角形8个",
    "taskicon": "icon_task_2",
    "textID": "57",
    "taskinfo": "Impact Triangle 8",
    "tasktype": "1",
    "target": "2",
    "count": "8",
    "limit": "0",
    "reward": "2"
  },
  {
    "id": "3",
    "node": "消灭弹簧5个",
    "taskicon": "icon_task_3",
    "textID": "58",
    "taskinfo": "Impact Spring 5",
    "tasktype": "1",
    "target": "3",
    "count": "5",
    "limit": "0",
    "reward": "2"
  },
  {
    "id": "4",
    "node": "消灭蹦床5个",
    "taskicon": "icon_task_4",
    "textID": "59",
    "taskinfo": "Impact Trampoline 5",
    "tasktype": "1",
    "target": "4",
    "count": "5",
    "limit": "0",
    "reward": "2"
  },
  {
    "id": "5",
    "node": "消灭椭圆5个",
    "taskicon": "icon_task_5",
    "textID": "60",
    "taskinfo": "Impact Ellipse 5",
    "tasktype": "1",
    "target": "5",
    "count": "5",
    "limit": "0",
    "reward": "2"
  },
  {
    "id": "6",
    "node": "消灭圆环5个",
    "taskicon": "icon_task_6",
    "textID": "61",
    "taskinfo": "Impact Ring 5",
    "tasktype": "1",
    "target": "6",
    "count": "5",
    "limit": "0",
    "reward": "2"
  },
  {
    "id": "7",
    "node": "在一次游戏中消灭方形15个",
    "taskicon": "icon_task_1",
    "textID": "62",
    "taskinfo": "Hit a square 30 in one play",
    "tasktype": "1",
    "target": "1",
    "count": "30",
    "limit": "1",
    "reward": "2"
  },
  {
    "id": "8",
    "node": "在一次游戏中消灭三角形4个",
    "taskicon": "icon_task_2",
    "textID": "63",
    "taskinfo": "Hit a triangle 5 in one play",
    "tasktype": "1",
    "target": "2",
    "count": "4",
    "limit": "1",
    "reward": "2"
  },
  {
    "id": "9",
    "node": "在一次游戏中消灭螺旋形3个",
    "taskicon": "icon_task_3",
    "textID": "64",
    "taskinfo": "Hit a Spiral 3 in one play",
    "tasktype": "1",
    "target": "3",
    "count": "3",
    "limit": "1",
    "reward": "3"
  },
  {
    "id": "10",
    "node": "在一次游戏中消灭直线3个",
    "taskicon": "icon_task_4",
    "textID": "65",
    "taskinfo": "Hit a straight 3 in one play",
    "tasktype": "1",
    "target": "4",
    "count": "3",
    "limit": "1",
    "reward": "3"
  },
  {
    "id": "11",
    "node": "在一次游戏中消灭椭圆3个",
    "taskicon": "icon_task_5",
    "textID": "66",
    "taskinfo": "Hit the ellipse 3 in one play",
    "tasktype": "1",
    "target": "5",
    "count": "3",
    "limit": "1",
    "reward": "3"
  },
  {
    "id": "12",
    "node": "在一次游戏中消灭圆环3个",
    "taskicon": "icon_task_6",
    "textID": "67",
    "taskinfo": "Hit the ring 3 in one play",
    "tasktype": "1",
    "target": "6",
    "count": "3",
    "limit": "1",
    "reward": "3"
  },
  {
    "id": "13",
    "node": "不接触地面持续15秒",
    "taskicon": "icon_task_7",
    "textID": "68",
    "taskinfo": "Not touching the ground for 15 seconds.",
    "tasktype": "2",
    "target": "0",
    "count": "15",
    "limit": "0",
    "reward": "2"
  },
  {
    "id": "14",
    "node": "不接触地面持续25秒",
    "taskicon": "icon_task_7",
    "textID": "69",
    "taskinfo": "Not touching the ground for 25 seconds.",
    "tasktype": "2",
    "target": "0",
    "count": "25",
    "limit": "0",
    "reward": "4"
  },
  {
    "id": "15",
    "node": "在一次游戏中使用小冲刺10次",
    "taskicon": "icon_task_8",
    "textID": "70",
    "taskinfo": "Use sprint 10 times in one play",
    "tasktype": "3",
    "target": "0",
    "count": "10",
    "limit": "1",
    "reward": "4"
  },
  {
    "id": "16",
    "node": "使用30次小冲刺",
    "taskicon": "icon_task_8",
    "textID": "71",
    "taskinfo": "Use sprint 30 times",
    "tasktype": "3",
    "target": "0",
    "count": "30",
    "limit": "0",
    "reward": "2"
  },
  {
    "id": "17",
    "node": "在一次游戏中触发大冲刺2次",
    "taskicon": "icon_task_9",
    "textID": "72",
    "taskinfo": "Triggering 2 Super Sprints in one play",
    "tasktype": "4",
    "target": "0",
    "count": "2",
    "limit": "1",
    "reward": "4"
  },
  {
    "id": "18",
    "node": "触发5次大冲刺",
    "taskicon": "icon_task_9",
    "textID": "73",
    "taskinfo": "Triggering 5 Super Sprints",
    "tasktype": "4",
    "target": "0",
    "count": "5",
    "limit": "0",
    "reward": "2"
  }
]